capyt/VERSION
capyt/__init__.py
capyt/capyt.py
capyt-1.1.post1.dist-info/METADATA
capyt-1.1.post1.dist-info/RECORD
capyt-1.1.post1.dist-info/WHEEL
capyt-1.1.post1.dist-info/entry_points.txt
capyt-1.1.post1.dist-info/top_level.txt
