Metadata-Version: 2.1
Name: capyt
Version: 1.1.post1
Summary: A python3 CLI utility to interface with cpy.pt
Home-page: https://github.com/lbatalha/capyt
Author: Luis Batalha
Author-email: author@example.com
License: MIT
Platform: UNKNOWN
Classifier: Programming Language :: Python :: 3
Classifier: License :: OSI Approved :: MIT License
Classifier: Operating System :: OS Independent
Classifier: Natural Language :: English
Classifier: Topic :: Utilities
Requires-Dist: requests
